django_auditor_logs/__init__.py
django_auditor_logs/admin.py
django_auditor_logs/apps.py
django_auditor_logs/metadata.py
django_auditor_logs/models.py
django_auditor_logs/tests.py
django_auditor_logs/views.py
django_auditor_logs/auditor_schema/__init__.py
django_auditor_logs/auditor_schema/builder.py
django_auditor_logs/middleware/__init__.py
django_auditor_logs/middleware/metadata_middleware.py
django_auditor_logs-2.0.0.dist-info/LICENSE
django_auditor_logs-2.0.0.dist-info/METADATA
django_auditor_logs-2.0.0.dist-info/WHEEL
django_auditor_logs-2.0.0.dist-info/top_level.txt
django_auditor_logs-2.0.0.dist-info/RECORD
