Metadata-Version: 2.1
Name: django_auditor_logs
Version: 2.0.0
Summary: Package for easy creation of audit logs in Django projects
Home-page: https://90horasporsemana.com
Author: Yeison Fernandez
Author-email: contacto@90horasporsemana.com
License: MIT
Classifier: Environment :: Web Environment
Classifier: Framework :: Django
Classifier: Intended Audience :: Developers
Classifier: License :: OSI Approved :: MIT License
Classifier: Programming Language :: Python :: 3
Classifier: Topic :: Software Development :: Libraries :: Application Frameworks
Requires-Python: >=3.6
License-File: LICENSE
Requires-Dist: Django >=2.2
